{
  "collectionName": "components_location_location_heroes",
  "info": {
    "displayName": "Location Hero",
    "description": ""
  },
  "options": {},
  "attributes": {
    "title_first_line": {
      "type": "string",
      "required": true
    },
    "title_second_line": {
      "type": "string"
    },
    "description": {
      "type": "text",
      "required": true
    },
    "cta": {
      "type": "string"
    },
    "description_under_cta": {
      "type": "string",
      "required": true
    },
    "background_image": {
      "type": "media",
      "multiple": false,
      "required": true,
      "allowedTypes": [
        "images"
      ]
    },
    "left_image": {
      "type": "media",
      "multiple": false,
      "required": false,
      "allowedTypes": [
        "images"
      ]
    },
    "right_image": {
      "type": "media",
      "multiple": false,
      "required": false,
      "allowedTypes": [
        "images"
      ]
    },
    "mobile_background_image": {
      "allowedTypes": [
        "images"
      ],
      "type": "media",
      "multiple": false
    }
  }
}
